design/base_reg/rtl/base_reg.v
module base_reg #(
    parameter WID = 8 
) (
    // General // 
    input wire [    0:0] clk     , // clock signal
    input wire [    0:0] rst_n   , // Async reset, active low
    // Input control // 
    input wire [    0:0] en      , // Sample input enable
    // Input data // 
    input wire [WID-1:0] data_in , // Input data
    // Output data // 
    output reg [WID-1:0] data_out  // Output data
);

// Internal wires // 
wire [WID-1:0] data_out_next ;  // Next data out value

// data_out register //
assign data_out_next = (en) ? data_in : data_out ; // If enable, sample data in

always @( posedge clk, negedge rst_n ) begin 
    if (!rst_n) begin // Reset
        data_out <= {WID{1'b0}} ; 
    end
    else begin // Sample
        data_out <= data_out_next ; 
    end
end

endmodule

//|~~~~~~~~~~~~~~~~~~~~~~~~~~~~~~~~~~~~~~~~~~~~~~~|//
//|                                               |//
//| 1. Project  :  /home/etay-sela/design/veri_home/erim/vlib|//
//| 2. Author   :  Etay Sela                      |//
//| 3. Date     :  2024-06-08                     |//
//| 4. Version  :  v0.5.0                         |//
//|                                               |//
//|~~~~~~~~~~~~~~~~~~~~~~~~~~~~~~~~~~~~~~~~~~~~~~~|//

aligners/al_n2w/rtl/al_n2w.v
//|~~~~~~~~~~~~~~~~~~~~~~~~~~~~~~~~~~~~~~~~~~~~~~~~~~~~~~~~~~~~~~~~~~~~~~~~~~~~~~~~~~~~|//
//|                                                                                    |//
//| ~~ al_n2w ~~                                                                       |//
//|                                                                                    |//
//| Top-level description:                                                             |//
//|    1. Narrow-to-wide aligner                                                       |//
//|                                                                                    |//
//| Features:                                                                          |//
//|    1. Parameterized input width (WID_IN)                                           |//
//|    2. Parameterized output width (WID_OUT)                                         |//
//|       * Note that WID_OUT % WID_IN must be 0                                       |//
//|    3. Aligner advances only at input valid indicator high (vld_in)                 |//
//|    4. ter_in terminates the current transaction, outputs a valid out (vld_out)     |//
//|       indicator high and the currently gathered data as output (data_out)          |//
//|    5. ptr output signals the aligner internal pointer, it is a RATIO_WID bits       |//
//|       register that holds the number of valid inputs gathered in the aligner       |//
//|       a. ptr=0 --> aligner is empty                                                |//
//|       b. ptr=RATIO_VAL-1 --> aligner is full, next valid input will triger a       |//
//|          valid output                                                              |//
//|                                                                                    |//
//|~~~~~~~~~~~~~~~~~~~~~~~~~~~~~~~~~~~~~~~~~~~~~~~~~~~~~~~~~~~~~~~~~~~~~~~~~~~~~~~~~~~~|//

module al_n2w #(
    parameter WID_IN     =                4  , // Input width in bits
    parameter WID_OUT    =                16 , // Output width in bits
    localparam RATIO_VAL = WID_OUT / WID_IN  , // Ratio (input width / output width)
    localparam RATIO_WID = $clog2(RATIO_VAL) , // Ratio width in bits
    localparam INT_WID   = 32                  // Width of integer in bits
) (
    // General // 
    input wire [0:0]           clk      , // Clock signal
    input wire [0:0]           rst_n    , // Async reset, active low
    // Input controls // 
    input wire [0:0]           vld_in   , // Valid input indicator
    input wire [0:0]           ter      , // Terminate transaction, active high
    // Input data // 
    input wire [WID_IN-1:0]    data_in  , // Input data
    // Output controls // 
    output reg [0:0]           vld_out  , // Valid output indicator
    // Output data // 
    output reg [WID_OUT-1:0]   data_out , // Output data
    // Output debug // 
    output reg [RATIO_WID-1:0] ptr      , // Aligner pointer counter
    output reg                 full     , // Aligner is full
    output reg                 empty      // Aligner is empty
);

// Internal wires // 
wire                 clr_ptr_cond ; // condition to clear pointer
wire [RATIO_WID-1:0] ptr_plus1    ; // pointer plus 1
wire [RATIO_WID-1:0] ptr_next     ; // next pointer value
wire                 vld_out_next ; // next valid output indicator

// Aligner internal storage // 
wire [RATIO_VAL-2:0] [WID_IN-1:0] int_strg ; // Internal storage the size of (RATIO_VAL-1) * WID_IN bits

// Aligner pointer assignments // 
assign full         = ({{(INT_WID-RATIO_WID){1'b0}}, ptr} == (RATIO_VAL-1))           ; // ptr reached limit
assign empty        = (ptr == {RATIO_WID{1'b0}})                                      ; // ptr is all 0's
assign ptr_plus1    = ptr + {{(RATIO_WID-1){1'b0}},1'b1}                              ; // ptr + 1 
assign clr_ptr_cond = ((ter) | (vld_in & full))                                       ; // Terminate transaction is active or aligner full and input is valid
assign ptr_next     = (clr_ptr_cond) ? {RATIO_WID{1'b0}} : (vld_in) ? ptr_plus1 : ptr ; // Clear if condition met, o.w inc only if valid input

// pointer register // 
always_ff @( posedge clk, negedge rst_n ) begin : ptr_reg
    if (!rst_n) begin // Reset
        ptr <= {RATIO_WID{1'b0}} ; 
    end
    else begin // Sample next value
        ptr <= ptr_next ; 
    end
end

// Sample aligner internal storage // 
genvar ii;
generate
    for (ii = 0 ; ii < RATIO_VAL-1 ; ii=ii+1) begin : gen_int_strg_reg_loop
        base_reg #(.WID(WID_IN)) i_base_reg (
            .clk       (clk                                                  ),
            .rst_n     (rst_n                                                ),
            .en        ((ii == {{(INT_WID-RATIO_WID){1'b0}}, ptr}) & (vld_in)), // Aligner ptr points to me and input is valid
            .data_in   (data_in                                              ),
            .data_out  (int_strg[ii]                                         )
        );
    end
endgenerate

// valid out logic // 
assign vld_out = (full & vld_in) ; 

// Data output assembly // 
assign data_out = {data_in, int_strg} ; // Output data is the concat of input data at the MSword and int_strg after that

initial begin
    $dumpfile("dump.vcd");
    $dumpvars(1, al_n2w);
end

endmodule

aligners/al_n2w/tb/dump.vcd
$date
	Wed Mar 13 18:39:23 2024
$end
$version
	Icarus Verilog
$end
$timescale
	1ps
$end
$scope module al_n2w $end
$var wire 1 ! clk $end
$var wire 1 " clr_ptr_cond $end
$var wire 4 # data_in [3:0] $end
$var wire 1 $ rst_n $end
$var wire 1 % ter $end
$var wire 1 & vld_in $end
$var wire 1 ' vld_out $end
$var wire 2 ( ptr_plus1 [1:0] $end
$var wire 2 ) ptr_next [1:0] $end
$var wire 12 * int_strg [11:0] $end
$var wire 1 + full $end
$var wire 1 , empty $end
$var wire 16 - data_out [15:0] $end
$var parameter 32 . INT_WID $end
$var parameter 32 / RATIO_VAL $end
$var parameter 32 0 RATIO_WID $end
$var parameter 32 1 WID_IN $end
$var parameter 32 2 WID_OUT $end
$var reg 2 3 ptr [1:0] $end
$upscope $end
$enddefinitions $end
$comment Show the parameter values. $end
$dumpall
b10000 2
b100 1
b10 0
b100 /
b100000 .
$end
#0
$dumpvars
b0 3
b0 -
1,
0+
b0 *
b0 )
b1 (
0'
0&
0%
0$
b0 #
0"
1!
$end
#500
0!
#1000
b1 )
b1001000000000000 -
b1001 #
1&
1$
1!
#1500
0!
#2000
b1010 #
b10 )
0,
b10 (
b1 3
b1010000000001001 -
b1001 *
1!
#2500
0!
#3000
b1 #
b11 )
b11 (
b10 3
b1000010101001 -
b10101001 *
1!
#3500
0!
#4000
b1000 #
1"
b0 )
1'
1+
b0 (
b11 3
b1000000110101001 -
b110101001 *
1!
#4500
0!
#5000
b1100000110101001 -
b1100 #
b1 )
0"
0'
0+
1,
b1 (
b0 3
1!
#5500
0!
#6000
b1011 #
b10 )
0,
b10 (
b1 3
b1011000110101100 -
b110101100 *
1!
#6500
0!
#7000
b1110 #
b11 )
b11 (
b10 3
b1110000110111100 -
b110111100 *
1!
#7500
0!
#8000
b0 #
1"
b0 )
1'
1+
b0 (
b11 3
b111010111100 -
b111010111100 *
1!
#8500
0!
#9000
b1111010111100 -
b1 #
b1 )
0"
0'
0+
1,
b1 (
b0 3
1!
#9500
0!
#10000
b1010 #
b10 )
0,
b10 (
b1 3
b1010111010110001 -
b111010110001 *
1!
#10500
0!
#11000
b1001 #
b11 )
b11 (
b10 3
b1001111010100001 -
b111010100001 *
1!
#11500
0!
#12000
b1 #
1"
b0 )
1'
1+
b0 (
b11 3
b1100110100001 -
b100110100001 *
1!
#12500
0!
#13000
b1001100110100001 -
b1001 #
b1 )
0"
0'
0+
1,
b1 (
b0 3
1!
#13500
0!
#14000
b11 #
b10 )
0,
b10 (
b1 3
b11100110101001 -
b100110101001 *
1!
#14500
0!
#15000
b100 #
b11 )
b11 (
b10 3
b100100100111001 -
b100100111001 *
1!
#15500
0!
#16000
b1101 #
1"
b0 )
1'
1+
b0 (
b11 3
b1101010000111001 -
b10000111001 *
1!
#16500
0!
#17000
b1001010000111001 -
b1001 #
b1 )
0"
0'
0+
1,
b1 (
b0 3
1!
#17500
0!
#18000
b1101010000111001 -
b1101 #
b10 )
0,
b10 (
b1 3
1!
#18500
0!
#19000
b111 #
b11 )
b11 (
b10 3
b111010011011001 -
b10011011001 *
1!
#19500
0!
#20000
b1010 #
1"
b0 )
1'
1+
b0 (
b11 3
b1010011111011001 -
b11111011001 *
1!
#20500
0!
#21000
b11011111011001 -
b11 #
b1 )
0"
0'
0+
1,
b1 (
b0 3
1!
#21500
0!
#22000
b100 #
b10 )
0,
b10 (
b1 3
b100011111010011 -
b11111010011 *
1!
#22500
0!
#23000
b1100 #
b11 )
b11 (
b10 3
b1100011101000011 -
b11101000011 *
1!
#23500
0!
#24000
b11 #
1"
b0 )
1'
1+
b0 (
b11 3
b11110001000011 -
b110001000011 *
1!
#24500
0!
#25000
b0 *
b0 -
b0 #
0&
0$
b0 )
0"
0'
0+
1,
b1 (
b0 3
1!
